Metadata-Version: 2.1
Name: elloh2
Version: 0.0.2
Summary: A small example package
Requires-Python: >=3.11
Requires-Dist: sparklog
